taichi_extras/__init__.py
taichi_extras/mesh/__init__.py
taichi_extras/mesh/obj.py
taichi_extras/optimize/__init__.py
taichi_extras/optimize/minimize/__init__.py
taichi_extras/optimize/minimize/gradient_descent/__init__.py
taichi_extras/optimize/minimize/gradient_descent/adam.py
taichi_extras/spatial/__init__.py
taichi_extras/spatial/transform.py
taichi_extras/utils/__init__.py
taichi_extras/utils/field/__init__.py
taichi_extras/utils/field/like.py
taichi_extras-0.1.0.dist-info/METADATA
taichi_extras-0.1.0.dist-info/WHEEL
taichi_extras-0.1.0.dist-info/RECORD
